setup.py
BGdistributions/Binomialdistribution.py
BGdistributions/Gaussiandistribution.py
BGdistributions/Generaldistribution.py
BGdistributions/__init__.py
BGdistributions.egg-info/PKG-INFO
BGdistributions.egg-info/SOURCES.txt
BGdistributions.egg-info/dependency_links.txt
BGdistributions.egg-info/not-zip-safe
BGdistributions.egg-info/top_level.txt